Workbook

Sheet Raw_Export
A1: MidCore Industries Pvt Ltd - Budget vs Actuals RAW EXTRACT (UNPROCESSED)
A2: Extracted: 07-Aug-2026 14:41 IST | Source systems: SAP + Excel manual + legacy | Confidential
A4: Month / Period | B4: Fin Year | C4: Qtr | D4: Catgory | E4: LineItem | F4: Budget Amt | G4: Actual Amt | H4: Comments / Assumptions | I4: Flag | J4: Origin | K4: Notes2
A5: Jan-23 | C5: Q4 | D5: Cost | E5: HR | F5: 14.0 | G5: 13.5 | H5: Salaries + benefits + attrition replacement; slight overrun from mid-year hiring | I5: flag | J5: user_upload
A6: February 2024 | B6: FY24 | C6: q4 | D6: Revenue | E6: Product B | F6: 6160000 | H6: Legacy product line; declining due to market share loss; budgeted conservatively | J6: csv_import | K6: duplicate?
A7: Feb-24 | B7: FY24 | C7: Q4 | D7: Cost | E7: Finance & Admin | F7: 8.8 | G7: 8.8 | H7: Compliance, audit, office admin; tightly controlled; near-budget historically | I7: 1 | J7: legacy_system
A8: Aug-23 | B8: FY24 | C8: Q2 | D8: Cost | E8: Markting | F8: 18 | G8: 19.98 | H8: Brand + digital spends; FY24 overrun due to new product launch campaign | I8: check | J8: SAP_dump_v2
A9: Mar-24 | B9: FY24 | C9: Q4 | D9: Cost | E9: Finance & Admin | F9: Rs. 7.7 | G9: 7.85 L | H9: Compliance, audit, office admin; tightly controlled; near-budget historically | I9: flag | J9: export_apr.xlsx
A10: Mar-23 | B10: 23 | C10: Q4 | D10: Expenses | E10: Operations | F10: Rs. 78.75 | G10: 84.26 | H10: Manufacturing + COGS + overhead; 45% of revenue; input cost inflation trend FY24 | I10: 0 | J10: csv_import | K10: duplicate?
A11: Jun 23 | B11: FY24 | C11: Q1 | D11: Revenue | E11: Services | F11: 42 | G11: 46.2 | H11: After-sales and maintenance contracts; growing segment; sticky recurring revenue | I11: 0 | J11: export_apr.xlsx | K11: duplicate?
A12: 2024-01 | B12: FY24 | C12: Q4 | D12: Cost | E12: sales | F12: 24.75 | G12: 2525000 | H12: Field sales team + incentive payouts; ~10% of revenue; stable cost base | I12: 1 | J12: user_upload | K12: verify this
A13: Mar-23 | B13: FY23 | C13: Q4 | D13: Cost | E13: Finance & Admin | F13: 7.0 | G13: Rs. 7.14 | H13: Compliance, audit, office admin; tightly controlled; near-budget historically | I13: 1 | J13: csv_import
A14: Jul-22 | B14: FY23 | C14: Q2 | D14: Cost | E14: Finance & Admin | F14: 8.00 L | G14: 8.16 | H14: Compliance, audit, office admin; tightly controlled; near-budget historically | I14: 1 | J14: csv_import | K14: verify this
A15: SEP-22 | B15: FY23 | C15: Quarter 2 | D15: Revenue | E15: Services | F15: 40 | G15: 43,2 | H15: After-sales and maintenance contracts; growing segment; sticky recurring revenue | J15: manual_entry
A16: Feb-24 | B16: FY24 | C16: Q4 | D16: Cost | E16: Marketting | F16: 18 | G16: 19.8 | H16: BRAND + DIGITAL SPENDS; FY24 OVERRUN DUE TO NEW PRODUCT LAUNCH CAMPAIGN | I16: 1 | J16: legacy_system
A17: Nov-23 | B17: N/A | C17: Qtr 3 | D17: COST | E17: People | F17: 18.15 | G17: 19.24 | H17: Salaries + benefits + attrition replacement; slight overrun from mid-year hiring | I17: 0 | J17: SAP_dump_v2
A18: Jun-22 | B18: FY23 | C18: Q1 | D18: Cost | E18: hr | F18: 10.5 | G18: 10.71 lakhs | H18: Salaries + benefits + attrition replacement; slight overrun from mid-year hiring | I18: check | J18: manual_entry | K18: old value
A19: Jun-22 | B19: FY23 | C19: Q1 | D19: Cst | E19: Operations | F19: 78.75 | G19: ₹80.33 | H19: Manufacturing + COGS + overhead; 45% of revenue; input cost inflation trend FY24 | J19: SAP_dump_v2
A20: Jan-23 | B20: FY23 | C20: Q4 | D20: Revnue | E20: product a | F20: 1.1250e+02 | G20: 117 | H20: Core manufactured product; 50% revenue share; seasonal Q3 peak (festive demand) | I20: x | J20: SAP_dump_v2 | K20: reconcile
A21: Jun-22 | B21: FY23 | C21: Q1 | D21: Exp | E21: Sales | F21: 17.5 | G21: 17.85 | H21: Field sales team + incentive payouts; ~10% of revenue; stable cost base | I21: 0
A22: Oct-22 | B22: FY23 | C22: Q3 | D22: COST | E22: Sls | F22: 25.0 lakhs | G22: 25.75 | H22: Field sales team + incentive payouts; ~10% of revenue; stable cost base | I22: 0 | J22: csv_import | K22: verify this
A23: Oct-23 | B23: FY24 | C23: Q3 | D23: Cost | E23: Sales | F23: 27.5 | G23: 28.32 | H23: Field sales team + incentive payouts; ~10% of revenue; stable cost base | I23: 1 | K23: old value
A24: Jan-24 | B24: FY24 | C24: Q4 | D24: Rev | E24: product a | F24: 124.2 | G24: Rs. 130.41 | H24: CORE MANUFACTURED PRODUCT; 50% REVENUE SHARE; SEASONAL Q3 PEAK (FESTIVE DEMAND) | I24: x | J24: user_upload | K24: duplicate?
A25: Jul-23 | B25: FY24 | C25: Q2 | D25: Revenue | E25: Product A | F25: 11040000 | G25: 113.71 L | H25: Core manufactured product; 50% revenue share; seasonal Q3 peak (festive demand)
A26: Mar/24 | B26: FY24 | C26: Q4 | D26: Revenue | E26: Product B | F26: 53.9 | G26: 44.2 | H26: Legacy product line; declining due to market [truncated] | I26: x | K26: duplicate?
A27: Apr-22 | B27: FY23 | C27: Quarter 1 | D27: Cost | E27: Sales | F27: 0.0001 | G27: ₹17.68 | H27: Field sales team + incentive payouts; ... | I27: x | K27: ??
A28: 2023-05 | B28: FY24 | C28: Q1 | D28: Exp | E28: Sales | F28: 19.25 | G28: 19.06 | H28: Field sales team + incentive payouts; ... | I28: x | J28: user_upload | K28: reconcile
A29: Nov-23 | B29: Financial Year 24 | C29: Q3 | D29: Cost | E29: Finance/Admin | F29: Rs. 12.1 | G29: 12.34 | H29: Compliance, audit, office admin; tightly controlled; near-budget historically | I29: 1 | J29: csv_import
A30: 2022-06 | B30: FY23 | C30: Q1 | D30: Cost | E30: Brand | F30: 14 | G30: 14.56 | H30: Brand + digital spends; FY24 overrun due to new product launch campaign | I30: OK | J30: SAP_dump_v2 | K30: old value
A31: Mar-23 | B31: 23 | C31: Q4 | D31: Expenses | E31: Operations | F31: Rs. 78.75 | G31: 84.26 | H31: Manufacturing + COGS + overhead; 45% o... | I31: flag | J31: csv_import | K31: duplicate?
A32: Jan/24 | B32: FY 24 | C32: Q4 | D32: Cost | E32: OPERATIONS | F32: 108.9 | H32: Manufacturing + COGS + overhead; 45% of revenue; input cost inflation trend FY24 | I32: 1 | J32: manual_entry
A33: Dec/23 | B33: FY24 | C33: Q3 | D33: Revenue | E33: Product A | F33: 138 | G33: 143.52 | H33: Core manufactured product; 50% revenue share; seasonal Q3 peak (festive demand) | I33: 0 | J33: csv_import | K33: old value
A34: Jul-22 | C34: q2 | D34: Income | E34: Product A | F34: 100 | G34: 102 | H34: Core manufactured product; 50% revenue share; seasonal Q3 peak (festive demand) | J34: export_apr.xlsx | K34: duplicate?
A35: Jul 23 | B35: FY24 | C35: Q2 | D35: Cost | E35: Finance & Admin | F35: 8.8 | G35: 8.98 | H35: COMPLIANCE, AUDIT, OFFICE ADMIN; TIGHTLY CONTROLLED; NEAR-BUDGET HISTORICALLY | I35: flag | J35: manual_entry
A36: Oct-22 | B36: FY 23 | C36: Q3 | D36: Cost | E36: Marketing | F36: 20 | G36: ₹20.40 | H36: Brand + digital spends; FY24 overrun due to new product launch campaign | I36: 0 | J36: csv_import | K36: reconcile
A37: Feb-24 | B37: FY24 | C37: Q4 | D37: Costs | E37: HR | F37: 13.2 | G37: 13.73 | H37: Salaries + benefits + attrition replac... | I37: flag
A38: 3/1/2024 | B38: FY24 | C38: Q4 | D38: Cost | E38: People | F38: 11.55 | G38: Rs. 12.24 | H38: Salaries + benefits + attrition replac... | I38: 0 | J38: user_upload
A39: Mar-24 | B39: FY24 | C39: Q4 | D39: Rev | E39: Svc | F39: 42 | G39: 47.88 | H39: After-sales and maintenance contracts; growing segment; sticky recurring revenue | I39: x | J39: legacy_system
A40: Dec-23 | B40: FY24 | C40: Q3 | D40: Cst | E40: Manufacturing | F40: 121 | G40: 130.68 | H40: Manufacturing + COGS + overhead; 45% of revenue; input cost inflation trend FY24 | J40: manual_entry | K40: ??
A41: May-22 | B41: FY23 | C41: Q1 | D41: Revnue | E41: Services | F41: 35 | G41: 36.75 | H41: After-sales and maintenance contracts;... | J41: user_upload | K41: verify this
A42: 12/1/2022 | B42: 23 | C42: Q3 | D42: Exp | E42: Finance Admin | F42: 10.1 | G42: 10 | H42: Compliance, audit, office admin; tightly controlled; near-budget historically | I42: flag | J42: csv_import
A43: Feb-23 | B43: FY23 | C43: Q4 | D43: Revenue | E43: product a | F43: 100.0 lakhs | G43: 103 | H43: Core manufactured product; 50% revenue share; seasonal Q3 peak (festive demand) | I43: check | K43: ??
A44: Jul 22 | B44: FY23 | C44: Q2 | D44: Revenue | E44: Services | F44: 40 | G44: 42.8 | H44: After-sales and maintenance contracts; growing segment; sticky recurring revenue | I44: check | K44: verify this
A45: May-22 | B45: FY23 | C45: Q1 | D45: Cost | E45: Operations | F45: 78.75 | G45: 81.11 | H45: Manufacturing + COGS + overhead; 45% of revenue; input cost inflation trend FY24 | I45: check | J45: legacy_system | K45: verify this
A46: Jul-23 | B46: FY24 | C46: Qtr 2 | D46: Exp | E46: Marketting | F46: ₹18.00 | G46: 19,62 | H46: Brand + digital spends; FY24 overrun due to new product launch campaign | J46: manual_entry
A47: Dec-23 | B47: Financial Year 24 | C47: Q3 | D47: Revenue | E47: services | F47: 60 | G47: 66.6 | H47: After-sales and maintenance contracts; growing segment; sticky recurring revenue | I47: OK | J47: manual_entry | K47: ??
A48: August 2023 | B48: FY24 | C48: Q2 | D48: Sales Revenue | E48: Product A | F48: 110.4 | G48: 112.61 lakhs | H48: Core manufactured product; 50% revenue share; seasonal Q3 peak (festive demand) | I48: 1 | K48: old value
A49: Jun-23 | B49: FY24 | C49: Q1 | D49: Cost | E49: Fin & Admin | F49: 7.7 | G49: ₹7.78 | H49: Compliance, audit, office admin; tight... | I49: 0
A50: Aug-23 | B50: fy24 | C50: Q2 | D50: Cost | E50: Sales | F50: 22 | G50: 21.56 lakhs | H50: Field sales team + incentive payouts; ~10% of revenue; stable cost base | I50: 1 | J50: SAP_dump_v2 | K50: ??
A51: Mar-24 | B51: FY24 | C51: Q4 | D51: Cost | E51: Mkt | F51: 1.5750e+01 | G51: 17.01 | H51: Brand + digital spends; FY24 overrun d... | J51: manual_entry | K51: duplicate?
A52: Jun-23 | C52: Q1 | D52: Revenue | E52: Prod. A | F52: 96.6 | G52: 100.46 | H52: CORE MANUFACTURED PRODUCT; 50% REVENUE SHARE; SEASONAL Q3 PEAK (FESTIVE DEMAND) | I52: 1 | K52: duplicate?
A53: 11/1/2022 | B53: FY23 | C53: Q3 | D53: Cost | E53: HR | F53: 16.5 | G53: 17.32 | H53: Salaries + benefits + attrition replacement; slight overrun from mid-year hiring | J53: legacy_system
A54: Sep 23 | B54: FY24 | C54: Q2 | D54: Costs | E54: Human Resources | F54: 1320000 | G54: 13.73 | H54: Salaries + benefits + attrition replacement; slight overrun from mid-year hiring | I54: OK
A55: Mar/24 | B55: FY24 | C55: Q4 | D55: Revenue | E55: Product B | F55: 53.9 | G55: 44.2 | H55: Legacy product line; declining due to market share loss; budgeted conservatively | J55: user_upload | K55: verify this
A56: // TODO: data team to verify block starting here
A57: Aug-22 | B57: FY23 | C57: Q2 | D57: Cost | E57: Marketing | F57: 1.6000e+01 | G57: 16.8 | H57: Brand + digital spends; FY24 overrun d... | I57: flag | J57: export_apr.xlsx | K57: ??
A58: October 2022 | B58: fy23 | C58: Q3 | D58: Revenue | E58: After Sales | F58: Rs. 50.0 | G58: 54.5 | H58: After-sales and maintenance contracts; growing segment; sticky recurring revenue | J58: user_upload | K58: verify this
A59: Mar-23 | B59: FY23 | C59: Q4 | D59: Revenue | E59: PRODUCT B | F59: 52.5 | G59: 46.73 | H59: LEGACY PRODUCT LINE; DECLINING DUE TO MARKET SHARE LOSS; BUDGETED CONSERVATIVELY | I59: flag | J59: SAP_dump_v2
A60: May-23 | B60: FY24 | C60: Q1 | D60: Cost | E60: Operations | F60: Rs. 84.7 | G60: Rs. 89.78 | H60: Manufacturing + COGS + overhead; 45% o... | I60: check | J60: SAP_dump_v2 | K60: old value
A61: Jun/23 | B61: FY24 | C61: q1 | D61: Expense | E61: sales | F61: 19.25 | G61: 19.64 | H61: Field sales team + incentive payouts; ~10% of revenue; stable cost base | I61: flag | K61: reconcile
A62: DEC-23 | B62: Financial Year 24 | C62: Q3 | D62: Expenses | E62: Markting | F62: 24.98 | G62: 22.50 L | H62: Brand + digital spends; FY24 overrun due to new product launch campaign | I62: check | K62: reconcile
A63: Jul-22 | C63: q2 | D63: Income | E63: Product A | F63: 100 | G63: 102 | H63: Core manufactured product; 50% revenue... | I63: OK | J63: csv_import | K63: ??
A64: Sep-23 | B64: FY24 | C64: q2 | D64: Cost | E64: Manufacturing | F64: 96.8 | G64: 104.54 | H64: Manufacturing + COGS + overhead; 45% of revenue; input cost inflation trend FY24 | I64: check | J64: SAP_dump_v2 | K64: verify this
A65: Aug-23 | B65: FY24 | C65: Q2 | D65: Sales Revenue | E65: services | F65: 48 | G65: 52,8 | H65: After-sales and maintenance contracts; growing segment; sticky recurring revenue | I65: 0 | J65: legacy_system | K65: ??
A66: Aug-22 | B66: FY23 | C66: Q2 | D66: Revenue | E66: Prod B | F66: 60 | G66: 5580000 | H66: Legacy product line; declining due to market share loss; budgeted conservatively | I66: OK | K66: old value
A67: Jun-22 | B67: FY23 | C67: Q1 | D67: Cost | E67: Finance & Admin | F67: 7 | G67: 7.07 | H67: Compliance, audit, office admin; tightly controlled; near-budget historically | I67: x | J67: legacy_system | K67: reconcile
A68: Sep-23 | B68: FY24 | C68: 2 | D68: Revenue | E68: Product B | F68: 61.6 | G68: 54.21 | H68: Legacy product line; declining due to market share loss; budgeted conservatively | I68: 0 | J68: legacy_system | K68: reconcile
A69: Jan-24 | B69: FY24 | C69: Q4 | D69: Cost | E69: MARKETING | F69: 2.0250e+01 | G69: 22.07 lakhs | H69: Brand + digital spends; FY24 overrun due to new product launch campaign | I69: OK | J69: SAP_dump_v2
A70: Sep-22 | B70: FY23 | C70: Q2 | D70: Revenue | E70: Product B | F70: 60 | G70: 55.2 | H70: Legacy product line; declining due to market share loss; budgeted conservatively | I70: flag | J70: manual_entry | K70: ??
A71: Jan-24 | B71: FY24 | C71: Q4 | D71: Revenue | E71: After Sales | F71: 54 | G71: 61.02 | H71: After-sales and maintenance contracts; growing segment; sticky recurring revenue | I71: 0 | J71: export_apr.xlsx | K71: old value
A72: Feb/23 | B72: FY23 | C72: Q4 | D72: Expense | E72: marketing | F72: ₹16.00 | G72: 16,48 | H72: Brand + digital spends; FY24 overrun due to new product launch campaign | I72: 1 | J72: export_apr.xlsx
A73: FEB-23 | B73: FY 23 | C73: Q4 | D73: Revenue | E73: Product-B | F73: ₹60.00 | G73: 54 | H73: Legacy product line; declining due to market share loss; budgeted conservatively | I73: x | J73: SAP_dump_v2 | K73: reconcile
A74: Mar-23 | B74: FY23 | C74: Q4 | D74: Cost | E74: marketing | F74: 14 | G74: -450.5 | H74: Brand + digital spends; FY24 overrun due to new product launch campaign | J74: csv_import
A75: Apr-23 | B75: FY24 | C75: Q1 | D75: Cost | E75: Field Sales | F75: 19.2 | G75: 19.44 | H75: Field sales team + incentive payouts; ~10% of revenue; stable cost base | I75: 1 | J75: export_apr.xlsx | K75: ??
A76: Jan-23 | B76: FY23 | C76: Q4 | D76: Expenses | E76: Mkt | F76: 18 | G76: 18.72 | H76: Brand + digital spends; FY24 overrun due to new product launch campaign | I76: flag | J76: SAP_dump_v2
A77: Feb-23 | B77: FY23 | C77: Q4 | D77: Revenue | E77: Services | F77: 40 | G77: TBD | H77: After-sales and maintenance contracts; growing segment; sticky recurring revenue | I77: check | J77: SAP_dump_v2 | K77: reconcile
A78: Mar-23 | B78: FY23 | C78: Q4 | D78: Revenue | E78: Product A | F78: 87.5 | G78: 91.88 | H78: Core manufactured product; 50% revenue... | I78: x | J78: user_upload | K78: verify this
A79: Oct 23 | B79: FY24 | C79: Q3 | D79: Cost | E79: Marketting | F79: 22.5 | G79: 24.75 | H79: Brand + digital spends; FY24 overrun due to new product launch campaign | I79: flag | J79: SAP_dump_v2 | K79: ??
A80: may-22 | B80: FY23 | C80: Q1 | D80: Revenue | E80: Product A | F80: 8750000 | G80: 88.38 | H80: Core manufactured product; 50% revenue share; seasonal Q3 peak (festive demand) | I80: 0 | J80: manual_entry | K80: duplicate?
A81: Dec-23 | B81: FY24 | C81: Q3 | D81: Rev. | E81: Product B | F81: 77 | G81: 65,45 | H81: Legacy product line; declining due to market share loss; budgeted conservatively | I81: check | J81: user_upload | K81: reconcile
A82: JAN-23 | B82: FY23 | C82: Q4 | D82: Cost | E82: Finance/Admin | F82: 9 | G82: 9.09 | H82: Compliance, audit, office admin; tightly controlled; near-budget historically | I82: x | J82: user_upload | K82: old value
A83: Oct-23 | B83: FY24 | C83: Q3 | D83: Cost | E83: Manufacturing | F83: 121 | G83: 129.47 | H83: Manufacturing + COGS + overhead; 45% of revenue; input cost inflation trend FY24 | I83: OK | J83: export_apr.xlsx | K83: ??
A84: Aug-22 | B84: FY23 | C84: Q2 | D84: Cost | E84: Sales | F84: 20 | G84: 19.6 | H84: Field sales team + incentive payouts; ~10% of revenue; stable cost base | I84: 1 | J84: csv_import | K84: reconcile
A85: Nov-22 | B85: FY23 | C85: Q3 | D85: Cost | E85: Finance & Admin | F85: 11 | G85: 11.22 | H85: Compliance, audit, office admin; tightly controlled; near-budget historically | I85: x | J85: manual_entry
A86: JUL-22 | B86: FY23 | C86: Q2 | D86: Cst | E86: Sales Team | F86: 20,0 | G86: 20.2 | H86: Field sales team + incentive payouts; ~10% of revenue; stable cost base | J86: SAP_dump_v2 | K86: reconcile
A87: May-22 | B87: FY23 | C87: Q1 | D87: Cost | E87: Marketing | F87: 14 | G87: 14.28 | H87: Brand + digital spends; FY24 overrun due to new product launch campaign | I87: 0 | K87: duplicate?
A88: Jul-23 | B88: FY24 | C88: Q2 | D88: REVENUE | E88: Service | F88: 48 | G88: 53.28 | H88: AFTER-SALES AND MAINTENANCE CONTRACTS; GROWING SEGMENT; STICKY RECURRING REVENUE | I88: x | J88: user_upload | K88: verify this
A89: Mar 23 | B89: FY23 | C89: Q4 | D89: Revenue | E89: Services | F89: 35 | G89: Rs. 38.85 | H89: After-sales and maintenance contracts; growing segment; sticky recurring revenue | I89: x
A90: Sep-23 | B90: FY24 | C90: Qtr 2 | D90: Cost | E90: Sales | F90: 22 | G90: 2.2440e+01 | H90: Field sales team + incentive payouts; ~10% of revenue; stable cost base | I90: 1 | J90: legacy_system
A91: Sep 22 | B91: FY23 | C91: Q2 | D91: Cost | E91: Sales | F91: ₹20.00 | G91: 20.4 | H91: Field sales team + incentive payouts; ~10% of revenue; stable cost base | I91: 1 | J91: legacy_system | K91: duplicate?
A92: Nov/23 | B92: FY24 | C92: Q3 | D92: Income | E92: Product A | F92: 151.8 | G92: 160.91 | H92: Core manufactured product; 50% revenue share; seasonal Q3 peak (festive demand) | I92: check | J92: SAP_dump_v2 | K92: verify this
A93: 12/1/2023 | B93: FY24 | C93: Q3 | D93: Cost | E93: Fin & Admin | F93: 11,0 | G93: 11.11 | H93: Compliance, audit, office admin; tightly controlled; near-budget historically | I93: 1 | J93: user_upload | K93: old value
A94: 9/1/2022 | B94: FY23 | C94: Q2 | D94: Cost | E94: Human Resource | F94: 12 | G94: 12.36 | H94: Salaries + benefits + attrition replacement; slight overrun from mid-year hiring | I94: check | J94: user_upload | K94: old value
A95: Nov-22 | B95: FY 23 | C95: Q3 | D95: Cost | E95: Sales | F95: 27.5 | G95: 28.05 | H95: Field sales team + incentive payouts; ~10% of revenue; stable cost base | I95: x | J95: manual_entry | K95: verify this
A96: APR-22 | B96: FY23 | C96: Q1 | D96: Cost | E96: Finance & Admin | F96: 7.0 lakhs | G96: 7,07 | H96: Compliance, audit, office admin; tightly controlled; near-budget historically | I96: 1 | J96: user_upload
A97: Jul-22 | B97: FY23 | C97: Q2 | D97: Cost | F97: 12.48 | G97: 12 | H97: Salaries + benefits + attrition replacement; slight overrun from mid-year hiring | I97: check | J97: csv_import | K97: verify this
A98: Month | B98: FY | C98: Q | D98: Cat | E98: Item | F98: Bud | G98: Act | H98: Note | I98: Flg | J98: Src | K98: Tmp
A99: Mar-24 | B99: FY24 | C99: Q4 | D99: Cost | E99: Sales | F99: 19.25 | G99: 19.83 | H99: Field sales team + incentive payouts; ~10% of revenue; stable cost base | J99: export_apr.xlsx | K99: old value
A100: Jan-24 | B100: FY24 | C100: Q4 | D100: cost | E100: Finance & Admin | F100: 9.9 | G100: 10 | H100: Compliance, audit, office admin; tightly controlled; near-budget historically | I100: x | J100: csv_import
A101: Sep-23 | B101: FY24 | C101: Q2 | D101: Expenses | E101: Mktg | F101: ₹18.00 | G101: 20.34 | H101: Brand + digital spends; FY24 overrun due to new product launch campaign | I101: flag | K101: verify this
...

Sheet Raw_Export_Clean
A1: MidCore Industries Pvt Ltd — Budget vs Actual Data (FY2023–FY2024)
A2: Unit: ₹ Lakhs | Source: Synthetic dataset modelled on Indian mid-market manufacturing benchmarks
A3: Month | B3: FY | C3: Quarter | D3: Category | E3: Line Item | F3: Budget Reqired (₹ L) | G3: Actual Budget (₹ L) | H3: Assumption Note
A4: Apr-22 | B4: FY23 | C4: Q1 | D4: Revenue | E4: Product A | F4: 87.5 | G4: 89.25 | H4: Core manufactured product; 50% revenue share; seasonal Q3 peak (festive demand)
A5: Apr-22 | B5: FY23 | C5: Q1 | D5: Revenue | E5: Product B | F5: 52.5 | G5: 50.4 | H5: Legacy product line; declining due to market share loss; budgeted conservatively
A6: Apr-22 | B6: FY23 | C6: Q1 | D6: Revenue | E6: Services | F6: 35 | G6: 36.4 | H6: After-sales and maintenance contracts; growing segment; sticky recurring revenue
A7: Apr-22 | B7: FY23 | C7: Q1 | D7: Cost | E7: Operations | F7: 78.75 | G7: 80.33 | H7: Manufacturing + COGS + overhead; 45% of revenue; input cost inflation trend FY24
A8: Apr-22 | B8: FY23 | C8: Q1 | D8: Cost | E8: Sales | F8: 17.5 | G8: 17.68 | H8: Field sales team + incentive payouts; ~10% of revenue; stable cost base
A9: Apr-22 | B9: FY23 | C9: Q1 | D9: Cost | E9: Marketing | F9: 14 | G9: 14.42 | H9: Brand + digital spends; FY24 overrun due to new product launch campaign
A10: Apr-22 | B10: FY23 | C10: Q1 | D10: Cost | E10: HR | F10: 10.5 | G10: 10.71 | H10: Salaries + benefits + attrition replacement; slight overrun from mid-year hiring
A11: Apr-22 | B11: FY23 | C11: Q1 | D11: Cost | E11: Finance & Admin | F11: 7 | G11: 7.07 | H11: Compliance, audit, office admin; tightly controlled; near-budget historically
A12: May-22 | B12: FY23 | C12: Q1 | D12: Revenue | E12: Product A | F12: 87.5 | G12: 88.38 | H12: Core manufactured product; 50% revenue share; seasonal Q3 peak (festive demand)
A13: May-22 | B13: FY23 | C13: Q1 | D13: Revenue | E13: Product B | F13: 52.5 | G13: 49.88 | H13: Legacy product line; declining due to market share loss; budgeted conservatively
A14: May-22 | B14: FY23 | C14: Q1 | D14: Revenue | E14: Services | F14: 35 | G14: 36.75 | H14: After-sales and maintenance contracts; growing segment; sticky recurring revenue
A15: May-22 | B15: FY23 | C15: Q1 | D15: Cost | E15: Operations | F15: 78.75 | G15: 81.11 | H15: Manufacturing + COGS + overhead; 45% of revenue; input cost inflation trend FY24
... A195: Mar-24 | B195: FY24 | C195: Q4 | D195: Cost | E195: Finance & Admin | F195: 7.7 | G195: 7.85 | H195: Compliance, audit, office admin; tightly controlled; near-budget historically

Sheet Raw_Export_Cleaned
A1: Month | B1: FY | C1: Quarter | D1: Category | E1: Line Item | F1: Budget (₹ L) | G1: Actual (₹ L) | H1: Comments / Assumptions
A2: Apr-22 | B2: FY23 | C2: Q1 | D2: Cost | E2: HR | F2: 10.5 | G2: 10.71 | H2: Salaries + benefits + attrition replacement; slight overrun from mid-year hiring
A3: Apr-22 | B3: FY23 | C3: Q1 | D3: Cost | E3: Operations | F3: 78.75 | G3: 80.33 | H3: Manufacturing + COGS + overhead; 45% of revenue; input cost inflation trend FY24
A4: Apr-22 | B4: FY23 | C4: Q1 | D4: Revenue | E4: Product B | F4: 52.5 | G4: 50.4 | H4: LEGACY PRODUCT LINE; DECLINING DUE TO MARKET SHARE LOSS; BUDGETED CONSERVATIVELY
A5: Apr-22 | B5: FY23 | C5: Q1 | D5: Revenue | E5: Product A | F5: 87.5 | G5: 89.25 | H5: Core manufactured product; 50% revenue share; seasonal Q3 peak (festive demand)
A6: Apr-22 | B6: FY23 | C6: Q1 | D6: Cost | E6: Marketing | F6: 14 | G6: 14.42 | H6: Brand + digital spends; FY24 overrun due to new product launch campaign
A7: Apr-22 | B7: FY23 | C7: Q1 | D7: Revenue | E7: Services | F7: 35 | G7: 36.4 | H7: After-sales and maintenance contracts; growing segment; sticky recurring revenue
A8: Apr-22 | B8: FY23 | C8: Q1 | D8: Cost | E8: Finance & Admin | G8: 7.07 | H8: Compliance, audit, office admin; tightly controlled; near-budget historically
A9: Apr-22 | B9: FY23 | C9: Q1 | D9: Cost | E9: Sales | F9: 0.0001 | G9: 17.68 | H9: Field sales team + incentive payouts; ...
A10: Aug-22 | B10: FY23 | C10: Q2 | D10: Cost | E10: HR | F10: 12 | G10: 12.36 | H10: Salaries + benefits + attrition replacement; slight overrun from mid-year hiring
A11: Aug-22 | B11: FY23 | C11: Q2 | D11: Cost | E11: Operations | F11: 90 | G11: 92.7 | H11: Manufacturing + COGS + overhead; 45% of revenue; input cost inflation trend FY24
A12: Aug-22 | B12: FY23 | C12: Q2 | D12: Revenue | E12: Product A | F12: 100 | G12: 101 | H12: Core manufactured product; 50% revenue...
A13: Aug-22 | B13: FY23 | C13: Q2 | D13: Revenue | E13: Services | F13: 40 | G13: 42.4 | H13: After-sales and maintenance contracts; growing segment; sticky recurring revenue
A14: Aug-22 | B14: FY23 | C14: Q2 | D14: Cost | E14: Sales | F14: 20 | G14: 19.6 | H14: Field sales team + incentive payouts; ~10% of revenue; stable cost base
A15: Aug-22 | B15: FY23 | C15: Q2 | D15: Cost | E15: Marketing | F15: 16 | G15: 16.8 | H15: Brand + digital spends; FY24 overrun d...
A16: Aug-22 | B16: FY23 | C16: Q2 | D16: Revenue | E16: Product B | F16: 60 | G16: 55.8 | H16: Legacy product line; declining due to market share loss; budgeted conservatively
A17: Aug-22 | B17: FY23 | C17: Q2 | D17: Cost | E17: Finance & Admin | F17: 8 | H17: Compliance, audit, office admin; tightly controlled; near-budget historically
A18: Dec-22 | B18: FY23 | C18: Q3 | D18: Cost | E18: Operations | F18: 112.5 | G18: 118.12 | H18: Manufacturing + COGS + overhead; 45% of revenue; input cost inflation trend FY24
A19: Dec-22 | B19: FY23 | C19: Q3 | D19: Revenue | E19: Services | F19: 50 | G19: 54 | H19: After-sales and maintenance contracts; growing segment; sticky recurring revenue
A20: Dec-22 | B20: FY23 | C20: Q3 | D20: Cost | E20: HR | F20: 15 | G20: 15.45 | H20: Salaries + benefits + attrition replacement; slight overrun from mid-year hiring
A21: Dec-22 | B21: FY23 | C21: Q3 | D21: Revenue | E21: Product A | F21: 125 | G21: 128.75 | H21: Core manufactured product; 50% revenue...
A22: Dec-22 | B22: FY23 | C22: Q3 | D22: Cost | E22: Finance & Admin | F22: 10.1 | G22: 10 | H22: Compliance, audit, office admin; tightly controlled; near-budget historically
A23: Dec-22 | B23: FY23 | C23: Q3 | D23: Cost | E23: Sales | F23: 25 | H23: Field sales team + incentive payouts; ~10% of revenue; stable cost base
A24: Dec-22 | B24: FY23 | C24: Q3 | D24: Revenue | E24: Product B | G24: 68.25 | H24: Legacy product line; declining due to market share loss; budgeted conservatively
A25: Dec-22 | B25: FY23 | C25: Q3 | D25: Cost | E25: Marketing | G25: 21 | H25: Brand + digital spends; FY24 overrun due to new product launch campaign
A26: Feb-23 | B26: FY23 | C26: Q4 | D26: Cost | E26: Finance & Admin | F26: 8 | G26: 8 | H26: Compliance, audit, office admin; tightly controlled; near-budget historically
A27: Feb-23 | B27: FY23 | C27: Q4 | D27: Cost | E27: HR | F27: 12 | G27: 12.36 | H27: Salaries + benefits + attrition replacement; slight overrun from mid-year hiring
A28: Feb-23 | B28: FY23 | C28: Q4 | D28: Cost | E28: Sales | F28: 20 | G28: 20.2 | H28: FIELD SALES TEAM + INCENTIVE PAYOUTS; ~10% OF REVENUE; STABLE COST BASE
A29: Feb-23 | B29: FY23 | C29: Q4 | D29: Cost | E29: Operations | F29: 90 | G29: 94.5 | H29: Manufacturing + COGS + overhead; 45% of revenue; input cost inflation trend FY24
A30: Feb-23 | B30: FY23 | C30: Q4 | D30: Revenue | E30: Product B | F30: 60 | G30: 54 | H30: Legacy product line; declining due to market share loss; budgeted conservatively
A31: Feb-23 | B31: FY23 | C31: Q4 | D31: Cost | E31: Marketing | F31: 16 | G31: 16.48 | H31: Brand + digital spends; FY24 overrun due to new product launch campaign
A32: Feb-23 | B32: FY23 | C32: Q4 | D32: Revenue | E32: Product A | G32: 103 | H32: Core manufactured product; 50% revenue share; seasonal Q3 peak (festive demand)
A33: Feb-23 | B33: FY23 | C33: Q4 | D33: Revenue | E33: Services | F33: 40 | H33: After-sales and maintenance contracts; growing segment; sticky recurring revenue
A34: Jan-23 | B34: FY23 | C34: Q4 | D34: Cost | E34: HR | F34: 14 | G34: 13.5 | H34: Salaries + benefits + attrition replacement; slight overrun from mid-year hiring
A35: Jan-23 | B35: FY23 | C35: Q4 | D35: Revenue | E35: Services | F35: 45 | G35: 49.05 | H35: After-sales and maintenance contracts; growing segment; sticky recurring revenue
A36: Jan-23 | B36: FY23 | C36: Q4 | D36: Revenue | E36: Product B | F36: 67.5 | G36: 62.1 | H36: Legacy product line; declining due to market share loss; budgeted conservatively
A37: Jan-23 | B37: FY23 | C37: Q4 | D37: Cost | E37: Operations | F37: 101.25 | G37: 107.33 | H37: Manufacturing + COGS + overhead; 45% of revenue; input cost inflation trend FY24
A38: Jan-23 | B38: FY23 | C38: Q4 | D38: Revenue | E38: Product A | F38: 112.5 | G38: 117 | H38: Core manufactured product; 50% revenue share; seasonal Q3 peak (festive demand)
A39: Jan-23 | B39: FY23 | C39: Q4 | D39: Cost | E39: Finance & Admin | F39: 9 | G39: 9.09 | H39: Compliance, audit, office admin; tightly controlled; near-budget historically
A40: Jan-23 | B40: FY23 | C40: Q4 | D40: Cost | E40: Marketing | F40: 18 | G40: 18.72 | H40: Brand + digital spends; FY24 overrun due to new product launch campaign
A41: Jan-23 | B41: FY23 | C41: Q4 | D41: Cost | E41: Sales | G41: 22.95 | H41: FIELD SALES TEAM + INCENTIVE PAYOUTS; ~10% OF REVENUE; STABLE COST BASE
A42: Jul-22 | B42: FY23 | C42: Q2 | D42: Cost | E42: Operations | F42: 90 | G42: 93.6 | H42: Manufacturing + COGS + overhead; 45% of revenue; input cost inflation trend FY24
A43: Jul-22 | B43: FY23 | C43: Q2 | D43: Cost | E43: Marketing | F43: 16 | G43: 16.48 | H43: Brand + digital spends; FY24 overrun due to new product launch campaign
A44: Jul-22 | B44: FY23 | C44: Q2 | D44: Revenue | E44: Product B | F44: 60 | G44: 57 | H44: Legacy product line; declining due to ...
A45: Jul-22 | B45: FY23 | C45: Q2 | D45: Revenue | E45: Product A | F45: 100 | G45: 102 | H45: Core manufactured product; 50% revenue share; seasonal Q3 peak (festive demand)
A46: Jul-22 | B46: FY23 | C46: Q2 | D46: Revenue | E46: Services | F46: 40 | G46: 42.8 | H46: After-sales and maintenance contracts; growing segment; sticky recurring revenue
A47: Jul-22 | B47: FY23 | C47: Q2 | D47: Cost | E47: Finance & Admin | F47: 8 | G47: 8.16 | H47: Compliance, audit, office admin; tightly controlled; near-budget historically
A48: Jul-22 | B48: FY23 | C48: Q2 | D48: Cost | E48: Sales | F48: 20 | G48: 20.2 | H48: Field sales team + incentive payouts; ~10% of revenue; stable cost base
A49: Jun-22 | B49: FY23 | C49: Q1 | D49: Revenue | E49: Product A | F49: 87.5 | G49: 90.12 | H49: Core manufactured product; 50% revenue share; seasonal Q3 peak (festive demand)
A50: Jun-22 | B50: FY23 | C50: Q1 | D50: Revenue | E50: Product B | F50: 52.5 | G50: 49.35 | H50: Legacy product line; declining due to market share loss; budgeted conservatively
A51: Jun-22 | B51: FY23 | C51: Q1 | D51: Cost | E51: Marketing | F51: 14 | G51: 14.56 | H51: Brand + digital spends; FY24 overrun due to new product launch campaign
A52: Jun-22 | B52: FY23 | C52: Q1 | D52: Cost | E52: Operations | F52: 78.75 | G52: 80.33 | H52: Manufacturing + COGS + overhead; 45% of revenue; input cost inflation trend FY24
A53: Jun-22 | B53: FY23 | C53: Q1 | D53: Cost | E53: Sales | F53: 17.5 | G53: 17.85 | H53: Field sales team + incentive payouts; ~10% of revenue; stable cost base
A54: Jun-22 | B54: FY23 | C54: Q1 | D54: Cost | E54: Finance & Admin | F54: 7 | G54: 7.07 | H54: Compliance, audit, office admin; tightly controlled; near-budget historically
A55: Jun-22 | B55: FY23 | C55: Q1 | D55: Cost | E55: HR | F55: 10.5 | H55: Salaries + benefits + attrition replacement; slight overrun from mid-year hiring
A56: Jun-22 | B56: FY23 | C56: Q1 | D56: Revenue | E56: Services | F56: 35 | H56: After-sales and maintenance contracts; growing segment; sticky recurring revenue
A57: Mar-23 | B57: FY23 | C57: Q4 | D57: Cost | E57: HR | F57: 10.5 | G57: 11.03 | H57: Salaries + benefits + attrition replacement; slight overrun from mid-year hiring
A58: Mar-23 | B58: FY23 | C58: Q4 | D58: Cost | E58: Sales | F58: 17.5 | G58: 18.03 | H58: Field sales team + incentive payouts; ~10% of revenue; stable cost base
A59: Mar-23 | B59: FY23 | C59: Q4 | D59: Cost | E59: Operations | F59: 78.75 | G59: 84.26 | H59: Manufacturing + COGS + overhead; 45% of revenue; input cost inflation trend FY24
A60: Mar-23 | B60: FY23 | C60: Q4 | D60: Cost | E60: Finance & Admin | F60: 7 | G60: 7.14 | H60: Compliance, audit, office admin; tightly controlled; near-budget historically
A61: Mar-23 | B61: FY23 | C61: Q4 | D61: Revenue | E61: Product A | F61: 87.5 | G61: 91.88 | H61: Core manufactured product; 50% revenue...
A62: Mar-23 | B62: FY23 | C62: Q4 | D62: Revenue | E62: Product B | F62: 52.5 | G62: 46.73 | H62: LEGACY PRODUCT LINE; DECLINING DUE TO MARKET SHARE LOSS; BUDGETED CONSERVATIVELY
A63: Mar-23 | B63: FY23 | C63: Q4 | D63: Revenue | E63: Services | F63: 35 | G63: 38.85 | H63: After-sales and maintenance contracts; growing segment; sticky recurring revenue
A64: Mar-23 | B64: FY23 | C64: Q4 | D64: Cost | E64: Marketing | F64: 14 | G64: -450.5 | H64: Brand + digital spends; FY24 overrun due to new product launch campaign
A65: May-22 | B65: FY23 | C65: Q1 | D65: Cost | E65: Sales | F65: 17.5 | G65: 17.32 | H65: FIELD SALES TEAM + INCENTIVE PAYOUTS; ~10% OF REVENUE; STABLE COST BASE
A66: May-22 | B66: FY23 | C66: Q1 | D66: Revenue | E66: Services | F66: 35 | G66: 36.75 | H66: After-sales and maintenance contracts;...
A67: May-22 | B67: FY23 | C67: Q1 | D67: Cost | E67: Operations | F67: 78.75 | G67: 81.11 | H67: Manufacturing + COGS + overhead; 45% of revenue; input cost inflation trend FY24
A68: May-22 | B68: FY23 | C68: Q1 | D68: Revenue | E68: Product A | F68: 87.5 | G68: 88.38 | H68: Core manufactured product; 50% revenue share; seasonal Q3 peak (festive demand)
A69: May-22 | B69: FY23 | C69: Q1 | D69: Cost | E69: Marketing | F69: 14 | G69: 14.28 | H69: Brand + digital spends; FY24 overrun due to new product launch campaign
A70: May-22 | B70: FY23 | C70: Q1 | D70: Revenue | E70: Product B | G70: 49.88 | H70: Legacy product line; declining due to market share loss; budgeted conservatively
A71: May-22 | B71: FY23 | C71: Q1 | D71: Cost | E71: HR | F71: 10.5 | H71: Salaries + benefits + attrition replacement; slight overrun from mid-year hiring
A72: May-22 | B72: FY23 | C72: Q1 | D72: Cost | E72: Finance & Admin | H72: Compliance, audit, office admin; tightly controlled; near-budget historically
A73: Nov-22 | B73: FY23 | C73: Q3 | D73: Cost | E73: Marketing | F73: 22 | G73: 22.66 | H73: Brand + digital spends; FY24 overrun due to new product launch campaign
A74: Nov-22 | B74: FY23 | C74: Q3 | D74: Revenue | E74: Product A | F74: 137.5 | G74: 144.38 | H74: Core manufactured product; 50% revenue share; seasonal Q3 peak (festive demand)
A75: Nov-22 | B75: FY23 | C75: Q3 | D75: Cost | E75: Operations | F75: 123.75 | G75: 131.18 | H75: Manufacturing + COGS + overhead; 45% of revenue; input cost inflation trend FY24
A76: Nov-22 | B76: FY23 | C76: Q3 | D76: Cost | E76: Sales | F76: 27.5 | G76: 28.05 | H76: Field sales team + incentive payouts; ~10% of revenue; stable cost base
A77: Nov-22 | B77: FY23 | C77: Q3 | D77: Revenue | E77: Product B | F77: 82.5 | G77: 76.72 | H77: Legacy product line; declining due to market share loss; budgeted conservatively
A78: Nov-22 | B78: FY23 | C78: Q3 | D78: Revenue | E78: Services | F78: 55 | G78: 60.5 | H78: After-sales and maintenance contracts; growing segment; sticky recurring revenue
A79: Nov-22 | B79: FY23 | C79: Q3 | D79: Cost | E79: HR | F79: 16.5 | G79: 17.32 | H79: Salaries + benefits + attrition replacement; slight overrun from mid-year hiring
A80: Nov-22 | B80: FY23 | C80: Q3 | D80: Cost | E80: Finance & Admin | F80: 11 | G80: 11.22 | H80: Compliance, audit, office admin; tightly controlled; near-budget historically
A81: Oct-22 | B81: FY23 | C81: Q3 | D81: Revenue | E81: Product A | F81: 125 | G81: 130 | H81: Core manufactured product; 50% revenue...
A82: Oct-22 | B82: FY23 | C82: Q3 | D82: Cost | E82: Operations | F82: 112.5 | G82: 117 | H82: Manufacturing + COGS + overhead; 45% of revenue; input cost inflation trend FY24
A83: Oct-22 | B83: FY23 | C83: Q3 | D83: Revenue | E83: Product B | F83: 75 | G83: 70.5 | H83: Legacy product line; declining due to market share loss; budgeted conservatively
A84: Oct-22 | B84: FY23 | C84: Q3 | D84: Cost | E84: Marketing | F84: 20 | G84: 20.4 | H84: Brand + digital spends; FY24 overrun due to new product launch campaign
... A86: Oct-22 | B86: FY23 | C86: Q3 | D86: Cost | E86: Finance & Admin | F86: 10 | G86: -450.5 | H86: Compliance, audit, office admin; tightly controlled; near-budget historically
A87: Oct-22 | B87: FY23 | C87: Q3 | D87: Cost | E87: Sales | G87: 25.75 | H87: Field sales team + incentive payouts; ~10% of revenue; stable cost base
A88: Oct-22 | B88: FY23 | C88: Q3 | D88: Cost | E88: HR | F88: 0.0001 | G88: 15.6 | H88: Salaries + benefits + attrition replacement; slight overrun from mid-year hiring
A89: Sep-22 | B89: FY23 | C89: Q2 | D89: Revenue | E89: Product A | F89: 100 | G89: 103 | H89: Core manufactured product; 50% revenue share; seasonal Q3 peak (festive demand)
A90: Sep-22 | B90: FY23 | C90: Q2 | D90: Cost | E90: Operations | F90: 90 | G90: 94.5 | H90: Manufacturing + COGS + overhead; 45% of revenue; input cost inflation trend FY24
A91: Sep-22 | B91: FY23 | C91: Q2 | D91: Cost | E91: Finance & Admin | F91: 8 | G91: 8 | H91: Compliance, audit, office admin; tightly controlled; near-budget historically
A92: Sep-22 | B92: FY23 | C92: Q2 | D92: Cost | E92: HR | F92: 12 | G92: 12.36 | H92: Salaries + benefits + attrition replacement; slight overrun from mid-year hiring
A93: Sep-22 | B93: FY23 | C93: Q2 | D93: Cost | E93: Marketing | F93: 16 | G93: 16.64 | H93: Brand + digital spends; FY24 overrun due to new product launch campaign
A94: Sep-22 | B94: FY23 | C94: Q2 | D94: Revenue | E94: Services | F94: 40 | G94: 43.2 | H94: After-sales and maintenance contracts; growing segment; sticky recurring revenue
A95: Sep-22 | B95: FY23 | C95: Q2 | D95: Revenue | E95: Product B | F95: 60 | G95: 55.2 | H95: Legacy product line; declining due to market share loss; budgeted conservatively
A96: Sep-22 | B96: FY23 | C96: Q2 | D96: Cost | E96: Sales | F96: 20 | G96: 20.4 | H96: Field sales team + incentive payouts; ~10% of revenue; stable cost base
A97: Apr-23 | B97: FY24 | C97: Q1 | D97: Revenue | E97: Product A | F97: 96.6 | G97: 99.5 | H97: Core manufactured product; 50% revenue share; seasonal Q3 peak (festive demand)
A98: Apr-23 | B98: FY24 | C98: Q1 | D98: Cost | E98: Finance & Admin | F98: 7.7 | G98: 7.78 | H98: Compliance, audit, office admin; tightly controlled; near-budget historically
A99: Apr-23 | B99: FY24 | C99: Q1 | D99: Cost | E99: Marketing | F99: 15.75 | G99: 17.01 | H99: Brand + digital spends; FY24 overrun due to new product launch campaign
... A102: Apr-23 | B102: FY24 | C102: Q1 | D102: Cost | E102: Sales | F102: 19.2 | G102: 19.44 | H102: Field sales team + incentive payouts; ~10% of revenue; stable cost base
A103: Apr-23 | B103: FY24 | C103: Q1 | D103: Revenue | E103: Services | G103: 45.36 | H103: After-sales and maintenance contracts; growing segment; sticky recurring revenue
...

Sheet Variance Engine
A1: MidCore Industries Pvt Ltd — Variance Analysis Engine
A2: Formulas pull from Data sheet | Green = favourable | Amber = watch | Red = adverse
A3: Month | B3: FY | C3: Quarter | D3: Category | E3: Line Item | F3: Budget Reqired (₹ L) | G3: Actual Budget (₹ L) | H3: Abs Variance (₹ L) | I3: % Variance | J3: RAG Status | K3: YTD Cumulative Variance (₹ L)
A4: =Raw_Export_Clean!A4 -> Apr-22 | B4: =Raw_Export_Clean!B4 -> FY23 | C4: =Raw_Export_Clean!C4 -> Q1 | D4: =Raw_Export_Clean!D4 -> Revenue | E4: =Raw_Export_Clean!E4 -> Product A | F4: =Raw_Export_Clean!F4 -> 87.5 | G4: =Raw_Export_Clean!G4 -> 89.25 | H4: =G4-F4 -> 1.75 | I4: =IF(F4<>0,(G4-F4)/F4,0) -> 0.02 | J4: =IF(D4="Revenue",IF(I4>=0.02,"GREEN",IF(I4>=-0.05,"AMBER","RED")),IF(I4<=-0.02,"GREEN",IF(I4<=0.05,"AMBER","RED"))) -> GREEN | K4: =SUMPRODUCT((B$4:B4=B4)*(E$4:E4=E4)*H$4:H4) -> 1.75
A5: =Raw_Export_Clean!A5 -> Apr-22 | B5: =Raw_Export_Clean!B5 -> FY23 | C5: =Raw_Export_Clean!C5 -> Q1 | D5: =Raw_Export_Clean!D5 -> Revenue | E5: =Raw_Export_Clean!E5 -> Product B | F5: =Raw_Export_Clean!F5 -> 52.5 | G5: =Raw_Export_Clean!G5 -> 50.4 | H5: =G5-F5 -> -2.1 | I5: =IF(F5<>0,(G5-F5)/F5,0) -> -0.04 | J5: =IF(D5="Revenue",IF(I5>=0.02,"GREEN",IF(I5>=-0.05,"AMBER","RED")),IF(I5<=-0.02,"GREEN",IF(I5<=0.05,"AMBER","RED"))) -> AMBER | K5: =SUMPRODUCT((B$4:B5=B5)*(E$4:E5=E5)*H$4:H5) -> -2.1
A6: =Raw_Export_Clean!A6 -> Apr-22 | B6: =Raw_Export_Clean!B6 -> FY23 | C6: =Raw_Export_Clean!C6 -> Q1 | D6: =Raw_Export_Clean!D6 -> Revenue | E6: =Raw_Export_Clean!E6 -> Services | F6: =Raw_Export_Clean!F6 -> 35 | G6: =Raw_Export_Clean!G6 -> 36.4 | H6: =G6-F6 -> 1.4 | I6: =IF(F6<>0,(G6-F6)/F6,0) -> 0.04 | J6: =IF(D6="Revenue",IF(I6>=0.02,"GREEN",IF(I6>=-0.05,"AMBER","RED")),IF(I6<=-0.02,"GREEN",IF(I6<=0.05,"AMBER","RED"))) -> GREEN | K6: =SUMPRODUCT((B$4:B6=B6)*(E$4:E6=E6)*H$4:H6) -> 1.4
A7: =Raw_Export_Clean!A7 -> Apr-22 | B7: =Raw_Export_Clean!B7 -> FY23 | C7: =Raw_Export_Clean!C7 -> Q1 | D7: =Raw_Export_Clean!D7 -> Cost | E7: =Raw_Export_Clean!E7 -> Operations | F7: =Raw_Export_Clean!F7 -> 78.75 | G7: =Raw_Export_Clean!G7 -> 80.33 | H7: =G7-F7 -> 1.58 | I7: =IF(F7<>0,(G7-F7)/F7,0) -> 0.020063492 | J7: =IF(D7="Revenue",IF(I7>=0.02,"GREEN",IF(I7>=-0.05,"AMBER","RED")),IF(I7<=-0.02,"GREEN",IF(I7<=0.05,"AMBER","RED"))) -> AMBER | K7: =SUMPRODUCT((B$4:B7=B7)*(E$4:E7=E7)*H$4:H7) -> 1.58
A8: =Raw_Export_Clean!A8 -> Apr-22 | B8: =Raw_Export_Clean!B8 -> FY23 | C8: =Raw_Export_Clean!C8 -> Q1 | D8: =Raw_Export_Clean!D8 -> Cost | E8: =Raw_Export_Clean!E8 -> Sales | F8: =Raw_Export_Clean!F8 -> 17.5 | G8: =Raw_Export_Clean!G8 -> 17.68 | H8: =G8-F8 -> 0.18 | I8: =IF(F8<>0,(G8-F8)/F8,0) -> 0.010285714 | J8: =IF(D8="Revenue",IF(I8>=0.02,"GREEN",IF(I8>=-0.05,"AMBER","RED")),IF(I8<=-0.02,"GREEN",IF(I8<=0.05,"AMBER","RED"))) -> AMBER | K8: =SUMPRODUCT((B$4:B8=B8)*(E$4:E8=E8)*H$4:H8) -> 0.18
A9: =Raw_Export_Clean!A9 -> Apr-22 | B9: =Raw_Export_Clean!B9 -> FY23 | C9: =Raw_Export_Clean!C9 -> Q1 | D9: =Raw_Export_Clean!D9 -> Cost | E9: =Raw_Export_Clean!E9 -> Marketing | F9: =Raw_Export_Clean!F9 -> 14 | G9: =Raw_Export_Clean!G9 -> 14.42 | H9: =G9-F9 -> 0.42 | I9: =IF(F9<>0,(G9-F9)/F9,0) -> 0.03 | J9: =IF(D9="Revenue",IF(I9>=0.02,"GREEN",IF(I9>=-0.05,"AMBER","RED")),IF(I9<=-0.02,"GREEN",IF(I9<=0.05,"AMBER","RED"))) -> AMBER | K9: =SUMPRODUCT((B$4:B9=B9)*(E$4:E9=E9)*H$4:H9) -> 0.42
A10: =Raw_Export_Clean!A10 -> Apr-22 | B10: =Raw_Export_Clean!B10 -> FY23 | C10: =Raw_Export_Clean!C10 -> Q1 | D10: =Raw_Export_Clean!D10 -> Cost | E10: =Raw_Export_Clean!E10 -> HR | F10: =Raw_Export_Clean!F10 -> 10.5 | G10: =Raw_Export_Clean!G10 -> 10.71 | H10: =G10-F10 -> 0.21 | I10: =IF(F10<>0,(G10-F10)/F10,0) -> 0.02 | J10: =IF(D10="Revenue",IF(I10>=0.02,"GREEN",IF(I10>=-0.05,"AMBER","RED")),IF(I10<=-0.02,"GREEN",IF(I10<=0.05,"AMBER","RED"))) -> AMBER | K10: =SUMPRODUCT((B$4:B10=B10)*(E$4:E10=E10)*H$4:H10) -> 0.21
A11: =Raw_Export_Clean!A11 -> Apr-22 | B11: =Raw_Export_Clean!B11 -> FY23 | C11: =Raw_Export_Clean!C11 -> Q1 | D11: =Raw_Export_Clean!D11 -> Cost | E11: =Raw_Export_Clean!E11 -> Finance & Admin | F11: =Raw_Export_Clean!F11 -> 7 | G11: =Raw_Export_Clean!G11 -> 7.07 | H11: =G11-F11 -> 0.07 | I11: =IF(F11<>0,(G11-F11)/F11,0) -> 0.01 | J11: =IF(D11="Revenue",IF(I11>=0.02,"GREEN",IF(I11>=-0.05,"AMBER","RED")),IF(I11<=-0.02,"GREEN",IF(I11<=0.05,"AMBER","RED"))) -> AMBER | K11: =SUMPRODUCT((B$4:B11=B11)*(E$4:E11=E11)*H$4:H11) -> 0.07
A12: =Raw_Export_Clean!A12 -> May-22 | B12: =Raw_Export_Clean!B12 -> FY23 | C12: =Raw_Export_Clean!C12 -> Q1 | D12: =Raw_Export_Clean!D12 -> Revenue | E12: =Raw_Export_Clean!E12 -> Product A | F12: =Raw_Export_Clean!F12 -> 87.5 | G12: =Raw_Export_Clean!G12 -> 88.38 | H12: =G12-F12 -> 0.88 | I12: =IF(F12<>0,(G12-F12)/F12,0) -> 0.010057143 | J12: =IF(D12="Revenue",IF(I12>=0.02,"GREEN",IF(I12>=-0.05,"AMBER","RED")),IF(I12<=-0.02,"GREEN",IF(I12<=0.05,"AMBER","RED"))) -> AMBER | K12: =SUMPRODUCT((B$4:B12=B12)*(E$4:E12=E12)*H$4:H12) -> 2.63
A13: =Raw_Export_Clean!A13 -> May-22 | B13: =Raw_Export_Clean!B13 -> FY23 | C13: =Raw_Export_Clean!C13 -> Q1 | D13: =Raw_Export_Clean!D13 -> Revenue | E13: =Raw_Export_Clean!E13 -> Product B | F13: =Raw_Export_Clean!F13 -> 52.5 | G13: =Raw_Export_Clean!G13 -> 49.88 | H13: =G13-F13 -> -2.62 | I13: =IF(F13<>0,(G13-F13)/F13,0) -> -0.049904762 | J13: =IF(D13="Revenue",IF(I13>=0.02,"GREEN",IF(I13>=-0.05,"AMBER","RED")),IF(I13<=-0.02,"GREEN",IF(I13<=0.05,"AMBER","RED"))) -> AMBER | K13: =SUMPRODUCT((B$4:B13=B13)*(E$4:E13=E13)*H$4:H13) -> -4.72
A14: =Raw_Export_Clean!A14 -> May-22 | B14: =Raw_Export_Clean!B14 -> FY23 | C14: =Raw_Export_Clean!C14 -> Q1 | D14: =Raw_Export_Clean!D14 -> Revenue | E14: =Raw_Export_Clean!E14 -> Services | F14: =Raw_Export_Clean!F14 -> 35 | G14: =Raw_Export_Clean!G14 -> 36.75 | H14: =G14-F14 -> 1.75 | I14: =IF(F14<>0,(G14-F14)/F14,0) -> 0.05 | J14: =IF(D14="Revenue",IF(I14>=0.02,"GREEN",IF(I14>=-0.05,"AMBER","RED")),IF(I14<=-0.02,"GREEN",IF(I14<=0.05,"AMBER","RED"))) -> GREEN | K14: =SUMPRODUCT((B$4:B14=B14)*(E$4:E14=E14)*H$4:H14) -> 3.15
A15: =Raw_Export_Clean!A15 -> May-22 | B15: =Raw_Export_Clean!B15 -> FY23 | C15: =Raw_Export_Clean!C15 -> Q1 | D15: =Raw_Export_Clean!D15 -> Cost | E15: =Raw_Export_Clean!E15 -> Operations | F15: =Raw_Export_Clean!F15 -> 78.75 | G15: =Raw_Export_Clean!G15 -> 81.11 | H15: =G15-F15 -> 2.36 | I15: =IF(F15<>0,(G15-F15)/F15,0) -> 0.029968254 | J15: =IF(D15="Revenue",IF(I15>=0.02,"GREEN",IF(I15>=-0.05,"AMBER","RED")),IF(I15<=-0.02,"GREEN",IF(I15<=0.05,"AMBER","RED"))) -> AMBER | K15: =SUMPRODUCT((B$4:B15=B15)*(E$4:E15=E15)*H$4:H15) -> 3.94
... A195: =Raw_Export_Clean!A195 -> Mar-24 | B195: =Raw_Export_Clean!B195 -> FY24 | C195: =Raw_Export_Clean!C195 -> Q4 | D195: =Raw_Export_Clean!D195 -> Cost | E195: =Raw_Export_Clean!E195 -> Finance & Admin | F195: =Raw_Export_Clean!F195 -> 7.7 | G195: =Raw_Export_Clean!G195 -> 7.85 | H195: =G195-F195 -> 0.15 | I195: =IF(F195<>0,(G195-F195)/F195,0) -> 0.019480519 | J195: =IF(D195="Revenue",IF(I195>=0.02,"GREEN",IF(I195>=-0.05,"AMBER","RED")),IF(I195<=-0.02,"GREEN",IF(I195<=0.05,"AMBER","RED"))) -> AMBER | K195: =SUMPRODUCT((B$4:B195=B195)*(E$4:E195=E195)*H$4:H195) -> 1.14

Sheet Scenario Analysis
A1: MidCore Industries Pvt Ltd — Scenario & Sensitivity Analysis
A2: Stress-tests FY24 P&L under revenue shortfall and cost overrun scenarios | Unit: ₹ Lakhs
A3: This sheet will contain: Two-variable sensitivity table | Scenario Manager (Base / Moderate Stress / Severe Stress)
A4: SECTION 1: FY24 BASE P&L SUMMARY
A5: Line Item | B5: Category | C5: Budget Reqired (₹ L) | D5: Actual Budget (₹ L) | E5: Abs Variance (₹ L) | F5: % Variance
A6: Product A | B6: Revenue | C6: =SUMPRODUCT((Raw_Export_Clean!$B$4:$B$195="FY24")*(Raw_Export_Clean!$E$4:$E$195="Product A")*Raw_Export_Clean!$F$4:$F$195) -> 1380 | D6: =SUMPRODUCT((Raw_Export_Clean!$B$4:$B$195="FY24")*(Raw_Export_Clean!$E$4:$E$195="Product A")*Raw_Export_Clean!$G$4:$G$195) -> 1436.59 | E6: =D6-C6 -> 56.59 | F6: =IF(C6<>0,(D6-C6)/C6,0) -> 0.041007246
A7: Product B | B7: Revenue | C7: =SUMPRODUCT((Raw_Export_Clean!$B$4:$B$195="FY24")*(Raw_Export_Clean!$E$4:$E$195="Product B")*Raw_Export_Clean!$F$4:$F$195) -> 770 | D7: =SUMPRODUCT((Raw_Export_Clean!$B$4:$B$195="FY24")*(Raw_Export_Clean!$E$4:$E$195="Product B")*Raw_Export_Clean!$G$4:$G$195) -> 667.43 | E7: =D7-C7 -> -102.57 | F7: =IF(C7<>0,(D7-C7)/C7,0) -> -0.13320779
A8: Services | B8: Revenue | C8: =SUMPRODUCT((Raw_Export_Clean!$B$4:$B$195="FY24")*(Raw_Export_Clean!$E$4:$E$195="Services")*Raw_Export_Clean!$F$4:$F$195) -> 600 | D8: =SUMPRODUCT((Raw_Export_Clean!$B$4:$B$195="FY24")*(Raw_Export_Clean!$E$4:$E$195="Services")*Raw_Export_Clean!$G$4:$G$195) -> 668.16 | E8: =D8-C8 -> 68.16 | F8: =IF(C8<>0,(D8-C8)/C8,0) -> 0.1136
A9: Operations | B9: Cost | C9: =SUMPRODUCT((Raw_Export_Clean!$B$4:$B$195="FY24")*(Raw_Export_Clean!$E$4:$E$195="Operations")*Raw_Export_Clean!$F$4:$F$195) -> 1210 | D9: =SUMPRODUCT((Raw_Export_Clean!$B$4:$B$195="FY24")*(Raw_Export_Clean!$E$4:$E$195="Operations")*Raw_Export_Clean!$G$4:$G$195) -> 1300.03 | E9: =D9-C9 -> 90.03 | F9: =IF(C9<>0,(D9-C9)/C9,0) -> 0.074404959
A10: Sales | B10: Cost | C10: =SUMPRODUCT((Raw_Export_Clean!$B$4:$B$195="FY24")*(Raw_Export_Clean!$E$4:$E$195="Sales")*Raw_Export_Clean!$F$4:$F$195) -> 275 | D10: =SUMPRODUCT((Raw_Export_Clean!$B$4:$B$195="FY24")*(Raw_Export_Clean!$E$4:$E$195="Sales")*Raw_Export_Clean!$G$4:$G$195) -> 278.07 | E10: =D10-C10 -> 3.07 | F10: =IF(C10<>0,(D10-C10)/C10,0) -> 0.011163636
A11: Marketing | B11: Cost | C11: =SUMPRODUCT((Raw_Export_Clean!$B$4:$B$195="FY24")*(Raw_Export_Clean!$E$4:$E$195="Marketing")*Raw_Export_Clean!$F$4:$F$195) -> 225 | D11: =SUMPRODUCT((Raw_Export_Clean!$B$4:$B$195="FY24")*(Raw_Export_Clean!$E$4:$E$195="Marketing")*Raw_Export_Clean!$G$4:$G$195) -> 248.25 | E11: =D11-C11 -> 23.25 | F11: =IF(C11<>0,(D11-C11)/C11,0) -> 0.10333333
A12: HR | B12: Cost | C12: =SUMPRODUCT((Raw_Export_Clean!$B$4:$B$195="FY24")*(Raw_Export_Clean!$E$4:$E$195="HR")*Raw_Export_Clean!$F$4:$F$195) -> 165 | D12: =SUMPRODUCT((Raw_Export_Clean!$B$4:$B$195="FY24")*(Raw_Export_Clean!$E$4:$E$195="HR")*Raw_Export_Clean!$G$4:$G$195) -> 172.41 | E12: =D12-C12 -> 7.41 | F12: =IF(C12<>0,(D12-C12)/C12,0) -> 0.044909091
A13: Finance & Admin | B13: Cost | C13: =SUMPRODUCT((Raw_Export_Clean!$B$4:$B$195="FY24")*(Raw_Export_Clean!$E$4:$E$195="Finance & Admin")*Raw_Export_Clean!$F$4:$F$195) -> 110 | D13: =SUMPRODUCT((Raw_Export_Clean!$B$4:$B$195="FY24")*(Raw_Export_Clean!$E$4:$E$195="Finance & Admin")*Raw_Export_Clean!$G$4:$G$195) -> 111.14 | E13: =D13-C13 -> 1.14 | F13: =IF(C13<>0,(D13-C13)/C13,0) -> 0.010363636
A14: Total Revenue | C14: =SUM(C6:C8) -> 2750 | D14: =SUM(D6:D8) -> 2772.18 | E14: =D14-C14 -> 22.18 | F14: =IF(C14<>0,(D14-C14)/C14,0) -> 0.0080654545
A15: Total Cost | C15: =SUM(C9:C13) -> 1985 | D15: =SUM(D9:D13) -> 2109.9 | E15: =D15-C15 -> 124.9 | F15: =IF(C15<>0,(D15-C15)/C15,0) -> 0.062921914
A16: Net P&L (Budget) | C16: =C14-C15 -> 765 | D16: =D14-D15 -> 662.28
A18: SECTION 2: SCENARIO INPUTS
A19: Input Parameter | B19: Value | C19: Meaning
A20: Revenue Stress % | B20: -0.05 | C20: Reduce total FY24 budgeted revenue by this %. Simulates demand shortfall or market loss.
A21: Cost Overrun % | B21: 0.06 | C21: Increase total FY24 budgeted costs by this %. Simulates input inflation or budget breach.
A22: Change the yellow cells above. All stressed figures in Section 3 update automatically.
A24: SECTION 3: STRESSED P&L
A25: Line Item | B25: Category | C25: Base Budget (₹ L) | D25: Stressed Revenue/Cost (₹ L) | E25: Stress Impact (₹ L)
A26: Product A | B26: Revenue | C26: =C6 -> 1380 | D26: =C26*(1+$B$20) -> 1311 | E26: =D26-C26 -> -69
A27: Product B | B27: Revenue | C27: =C7 -> 770 | D27: =C27*(1+$B$20) -> 731.5 | E27: =D27-C27 -> -38.5
A28: Services | B28: Revenue | C28: =C8 -> 600 | D28: =C28*(1+$B$20) -> 570 | E28: =D28-C28 -> -30
A29: Operations | B29: Cost | C29: =C9 -> 1210 | D29: =C29*(1+$B$21) -> 1282.6 | E29: =D29-C29 -> 72.6
A30: Sales | B30: Cost | C30: =C10 -> 275 | D30: =C30*(1+$B$21) -> 291.5 | E30: =D30-C30 -> 16.5
A31: Marketing | B31: Cost | C31: =C11 -> 225 | D31: =C31*(1+$B$21) -> 238.5 | E31: =D31-C31 -> 13.5
A32: HR | B32: Cost | C32: =C12 -> 165 | D32: =C32*(1+$B$21) -> 174.9 | E32: =D32-C32 -> 9.9
A33: Finance & Admin | B33: Cost | C33: =C13 -> 110 | D33: =C33*(1+$B$21) -> 116.6 | E33: =D33-C33 -> 6.6
A34: Stressed Total Revenue | C34: =SUM(C26:C28) -> 2750 | D34: =SUM(D26:D28) -> 2612.5 | E34: =D34-C34 -> -137.5
A35: Stressed Total Cost | C35: =SUM(C29:C33) -> 1985 | D35: =SUM(D29:D33) -> 2104.1 | E35: =D35-C35 -> 119.1
A36: Stressed Net P&L | C36: =C34-C35 -> 765 | D36: =D34-D35 -> 508.4 | E36: =D36-C36 -> -256.6
A37: P&L Impact as % of Base Budget P&L | E37: =IF(C36<>0,E36/C36,0) -> -0.33542484
A39: SECTION 4: NAMED SCENARIO COMPARISON
A40: Metric | B40: Base Case | C40: Moderate Stress | D40: Severe Stress
A41: Revenue Stress % | B41: 0 | C41: -0.05 | D41: -0.12
A42: Cost Overrun % | B42: 0 | C42: 0.03 | D42: 0.08
A43: Stressed Revenue (₹ L) | B43: 2750 | C43: 2612.5 | D43: 2420
A44: Stressed Cost (₹ L) | B44: 1985 | C44: 2044.55 | D44: 2143.8
A45: Net P&L (₹ L) | B45: 765 | C45: 567.95 | D45: 276.2
A46: P&L Margin % | B46: 0.2782 | C46: 0.2174 | D46: 0.1141 | H46: NP/TR*100
A47: P&L vs Base (₹ L) | B47: 0 | C47: =C45-B45 -> -197.05 | D47: =D45-B45 -> -488.8 | H47: M S S P&L -BASE CASE
A50: SECTION 5: SENSITIVITY TABLE — Net P&L (₹ Lakhs) by Revenue Shortfall x Cost Overrun
A51: Yellow cells = change scenario inputs above and this table updates | Red cells = P&L negative (loss territory)
A52: Rev Shortfall ↓ / Cost Overrun → | B52: 0 | C52: 0.03 | D52: 0.06 | E52: 0.09 | F52: 0.12
A53: 0 | B53: 765 | C53: 705.45 | D53: 645.9 | E53: 586.35 | F53: 526.8
A54: -0.03 | B54: 682.5 | C54: 622.95 | D54: 563.4 | E54: 503.85 | F54: 444.3
A55: -0.06 | B55: 600 | C55: 540.45 | D55: 480.9 | E55: 421.35 | F55: 361.8
A56: -0.09 | B56: 517.5 | C56: 457.95 | D56: 398.4 | E56: 338.85 | F56: 279.3
A57: -0.12 | B57: 435 | C57: 375.45 | D57: 315.9 | E57: 256.35 | F57: 196.8
A58: -0.15 | B58: 352.5 | C58: 292.95 | D58: 233.4 | E58: 173.85 | F58: 114.3
A60: Key finding: P&L turns negative when revenue falls 9%+ AND costs overrun 9%+. Management must prioritise defending revenue in Product B and capping Operations overrun.

Sheet Dashboard
A1: MidCore Industries Pvt Ltd — Executive Variance Dashboard (FY2023–FY2024)
A2: Budget vs Actual Analysis | Stress Test Summary | Management Actions | Unit: ₹ Lakhs | Q2: Line Item | R2: Budget Reqired (₹ L) | S2: Actual Budget (₹ L)
A3: This sheet will contain: KPI tiles | Variance waterfall chart | RAG summary | Management action flags | Q3: Product A | R3: =SUMPRODUCT((Raw_Export_Clean!$B$4:$B$195="FY24")*(Raw_Export_Clean!$E$4:$E$195="Product A")*Raw_Export_Clean!$F$4:$F$195) -> 1380 | S3: =SUMPRODUCT((Raw_Export_Clean!$B$4:$B$195="FY24")*(Raw_Export_Clean!$E$4:$E$195="Product A")*Raw_Export_Clean!$G$4:$G$195) -> 1436.59
A4: FY24 BUDGETED NET P&L | C4: FY24 ACTUAL NET P&L | F4: PRODUCT B VARIANCE | H4: SEVERE STRESS NET P&L | Q4: Product B | R4: =SUMPRODUCT((Raw_Export_Clean!$B$4:$B$195="FY24")*(Raw_Export_Clean!$E$4:$E$195="Product B")*Raw_Export_Clean!$F$4:$F$195) -> 770 | S4: =SUMPRODUCT((Raw_Export_Clean!$B$4:$B$195="FY24")*(Raw_Export_Clean!$E$4:$E$195="Product B")*Raw_Export_Clean!$G$4:$G$195) -> 667.43
A5: ='Scenario Analysis'!C16 -> 765 | C5: ='Scenario Analysis'!D16 -> 662.28 | F5: =SUMPRODUCT((Raw_Export_Clean!$B$4:$B$195="FY24")*(Raw_Export_Clean!$E$4:$E$195="Product B")*(Raw_Export_Clean!$G$4:$G$195-Raw_Export_Clean!$F$4:$F$195)) -> -102.57 | H5: =315.9 -> 315.9 | Q5: Services | R5: =SUMPRODUCT((Raw_Export_Clean!$B$4:$B$195="FY24")*(Raw_Export_Clean!$E$4:$E$195="Services")*Raw_Export_Clean!$F$4:$F$195) -> 600 | S5: =SUMPRODUCT((Raw_Export_Clean!$B$4:$B$195="FY24")*(Raw_Export_Clean!$E$4:$E$195="Services")*Raw_Export_Clean!$G$4:$G$195) -> 668.16
Q6: Operations | R6: =SUMPRODUCT((Raw_Export_Clean!$B$4:$B$195="FY24")*(Raw_Export_Clean!$E$4:$E$195="Operations")*Raw_Export_Clean!$F$4:$F$195) -> 1210 | S6: =SUMPRODUCT((Raw_Export_Clean!$B$4:$B$195="FY24")*(Raw_Export_Clean!$E$4:$E$195="Operations")*Raw_Export_Clean!$G$4:$G$195) -> 1300.03
A7: ₹ Lakhs | FY24 Plan | C7: ₹ Lakhs | FY24 Performance | F7: ₹ Lakhs | Total FY24 Underperformance | H7: ₹ Lakhs | At -12% Rev, +8% Cost | Q7: Sales | R7: =SUMPRODUCT((Raw_Export_Clean!$B$4:$B$195="FY24")*(Raw_Export_Clean!$E$4:$E$195="Sales")*Raw_Export_Clean!$F$4:$F$195) -> 275 | S7: =SUMPRODUCT((Raw_Export_Clean!$B$4:$B$195="FY24")*(Raw_Export_Clean!$E$4:$E$195="Sales")*Raw_Export_Clean!$G$4:$G$195) -> 278.07
Q8: Marketing | R8: =SUMPRODUCT((Raw_Export_Clean!$B$4:$B$195="FY24")*(Raw_Export_Clean!$E$4:$E$195="Marketing")*Raw_Export_Clean!$F$4:$F$195) -> 225 | S8: =SUMPRODUCT((Raw_Export_Clean!$B$4:$B$195="FY24")*(Raw_Export_Clean!$E$4:$E$195="Marketing")*Raw_Export_Clean!$G$4:$G$195) -> 248.25
Q9: HR | R9: =SUMPRODUCT((Raw_Export_Clean!$B$4:$B$195="FY24")*(Raw_Export_Clean!$E$4:$E$195="HR")*Raw_Export_Clean!$F$4:$F$195) -> 165 | S9: =SUMPRODUCT((Raw_Export_Clean!$B$4:$B$195="FY24")*(Raw_Export_Clean!$E$4:$E$195="HR")*Raw_Export_Clean!$G$4:$G$195) -> 172.41
Q10: Finance & Admin | R10: =SUMPRODUCT((Raw_Export_Clean!$B$4:$B$195="FY24")*(Raw_Export_Clean!$E$4:$E$195="Finance & Admin")*Raw_Export_Clean!$F$4:$F$195) -> 110 | S10: =SUMPRODUCT((Raw_Export_Clean!$B$4:$B$195="FY24")*(Raw_Export_Clean!$E$4:$E$195="Finance & Admin")*Raw_Export_Clean!$G$4:$G$195) -> 111.14
Q15: Month | R15: Budget Reqired (₹ L) | S15: Actual Budget (₹ L)
Q16: Apr-23 | R16: =SUMPRODUCT((Raw_Export_Clean!$A$4:$A$195="Apr-23")*(Raw_Export_Clean!$D$4:$D$195="Revenue")*Raw_Export_Clean!$F$4:$F$195) -> 192.5 | S16: =SUMPRODUCT((Raw_Export_Clean!$A$4:$A$195="Apr-23")*(Raw_Export_Clean!$D$4:$D$195="Revenue")*Raw_Export_Clean!$G$4:$G$195) -> 193.37
Q17: May-23 | R17: =SUMPRODUCT((Raw_Export_Clean!$A$4:$A$195="May-23")*(Raw_Export_Clean!$D$4:$D$195="Revenue")*Raw_Export_Clean!$F$4:$F$195) -> 192.5 | S17: =SUMPRODUCT((Raw_Export_Clean!$A$4:$A$195="May-23")*(Raw_Export_Clean!$D$4:$D$195="Revenue")*Raw_Export_Clean!$G$4:$G$195) -> 192.28
Q18: Jun-23 | R18: =SUMPRODUCT((Raw_Export_Clean!$A$4:$A$195="Jun-23")*(Raw_Export_Clean!$D$4:$D$195="Revenue")*Raw_Export_Clean!$F$4:$F$195) -> 192.5 | S18: =SUMPRODUCT((Raw_Export_Clean!$A$4:$A$195="Jun-23")*(Raw_Export_Clean!$D$4:$D$195="Revenue")*Raw_Export_Clean!$G$4:$G$195) -> 194.09
Q19: Jul-23 | R19: =SUMPRODUCT((Raw_Export_Clean!$A$4:$A$195="Jul-23")*(Raw_Export_Clean!$D$4:$D$195="Revenue")*Raw_Export_Clean!$F$4:$F$195) -> 220 | S19: =SUMPRODUCT((Raw_Export_Clean!$A$4:$A$195="Jul-23")*(Raw_Export_Clean!$D$4:$D$195="Revenue")*Raw_Export_Clean!$G$4:$G$195) -> 221.81
Q20: Aug-23 | R20: =SUMPRODUCT((Raw_Export_Clean!$A$4:$A$195="Aug-23")*(Raw_Export_Clean!$D$4:$D$195="Revenue")*Raw_Export_Clean!$F$4:$F$195) -> 220 | S20: =SUMPRODUCT((Raw_Export_Clean!$A$4:$A$195="Aug-23")*(Raw_Export_Clean!$D$4:$D$195="Revenue")*Raw_Export_Clean!$G$4:$G$195) -> 219
Q21: Sep-23 | R21: =SUMPRODUCT((Raw_Export_Clean!$A$4:$A$195="Sep-23")*(Raw_Export_Clean!$D$4:$D$195="Revenue")*Raw_Export_Clean!$F$4:$F$195) -> 220 | S21: =SUMPRODUCT((Raw_Export_Clean!$A$4:$A$195="Sep-23")*(Raw_Export_Clean!$D$4:$D$195="Revenue")*Raw_Export_Clean!$G$4:$G$195) -> 222.79
Q22: Oct-23 | R22: =SUMPRODUCT((Raw_Export_Clean!$A$4:$A$195="Oct-23")*(Raw_Export_Clean!$D$4:$D$195="Revenue")*Raw_Export_Clean!$F$4:$F$195) -> 275 | S22: =SUMPRODUCT((Raw_Export_Clean!$A$4:$A$195="Oct-23")*(Raw_Export_Clean!$D$4:$D$195="Revenue")*Raw_Export_Clean!$G$4:$G$195) -> 278.92
Q23: Nov-23 | R23: =SUMPRODUCT((Raw_Export_Clean!$A$4:$A$195="Nov-23")*(Raw_Export_Clean!$D$4:$D$195="Revenue")*Raw_Export_Clean!$F$4:$F$195) -> 302.5 | S23: =SUMPRODUCT((Raw_Export_Clean!$A$4:$A$195="Nov-23")*(Raw_Export_Clean!$D$4:$D$195="Revenue")*Raw_Export_Clean!$G$4:$G$195) -> 308.52
Q24: Dec-23 | R24: =SUMPRODUCT((Raw_Export_Clean!$A$4:$A$195="Dec-23")*(Raw_Export_Clean!$D$4:$D$195="Revenue")*Raw_Export_Clean!$F$4:$F$195) -> 275 | S24: =SUMPRODUCT((Raw_Export_Clean!$A$4:$A$195="Dec-23")*(Raw_Export_Clean!$D$4:$D$195="Revenue")*Raw_Export_Clean!$G$4:$G$195) -> 275.57
Q25: Jan-24 | R25: =SUMPRODUCT((Raw_Export_Clean!$A$4:$A$195="Jan-24")*(Raw_Export_Clean!$D$4:$D$195="Revenue")*Raw_Export_Clean!$F$4:$F$195) -> 247.5 | S25: =SUMPRODUCT((Raw_Export_Clean!$A$4:$A$195="Jan-24")*(Raw_Export_Clean!$D$4:$D$195="Revenue")*Raw_Export_Clean!$G$4:$G$195) -> 251.03
Q26: Feb-24 | R26: =SUMPRODUCT((Raw_Export_Clean!$A$4:$A$195="Feb-24")*(Raw_Export_Clean!$D$4:$D$195="Revenue")*Raw_Export_Clean!$F$4:$F$195) -> 220 | S26: =SUMPRODUCT((Raw_Export_Clean!$A$4:$A$195="Feb-24")*(Raw_Export_Clean!$D$4:$D$195="Revenue")*Raw_Export_Clean!$G$4:$G$195) -> 220.32
Q27: Mar-24 | R27: =SUMPRODUCT((Raw_Export_Clean!$A$4:$A$195="Mar-24")*(Raw_Export_Clean!$D$4:$D$195="Revenue")*Raw_Export_Clean!$F$4:$F$195) -> 192.5 | S27: =SUMPRODUCT((Raw_Export_Clean!$A$4:$A$195="Mar-24")*(Raw_Export_Clean!$D$4:$D$195="Revenue")*Raw_Export_Clean!$G$4:$G$195) -> 194.48
A33: RAG PERFORMANCE SUMMARY — FY24
A34: Line Item | B34: Category | C34: FY24 Budget (₹L) | D34: FY24 Actual (₹L) | E34: Variance (₹L) | F34: Variance % | G34: Status | H34: Management Signal
A35: Product A | B35: Revenue | C35: =SUMPRODUCT((Raw_Export_Clean!$B$4:$B$195="FY24")*(Raw_Export_Clean!$E$4:$E$195="Product A")*Raw_Export_Clean!$F$4:$F$195) -> 1380 | D35: =SUMPRODUCT((Raw_Export_Clean!$B$4:$B$195="FY24")*(Raw_Export_Clean!$E$4:$E$195="Product A")*Raw_Export_Clean!$G$4:$G$195) -> 1436.59 | E35: =D35-C35 -> 56.59 | F35: =IF(C35<>0,(D35-C35)/C35,0) -> 0.041007246 | G35: GREEN | H35: GROW — consistently above budget. Increase allocation in FY25 plan.
A36: Product B | B36: Revenue | C36: =SUMPRODUCT((Raw_Export_Clean!$B$4:$B$195="FY24")*(Raw_Export_Clean!$E$4:$E$195="Product B")*Raw_Export_Clean!$F$4:$F$195) -> 770 | D36: =SUMPRODUCT((Raw_Export_Clean!$B$4:$B$195="FY24")*(Raw_Export_Clean!$E$4:$E$195="Product B")*Raw_Export_Clean!$G$4:$G$195) -> 667.43 | E36: =D36-C36 -> -102.57 | F36: =IF(C36<>0,(D36-C36)/C36,0) -> -0.13320779 | G36: RED | H36: EXIT REVIEW — persistent underperformance. Initiate product review.
A37: Services | B37: Revenue | C37: =SUMPRODUCT((Raw_Export_Clean!$B$4:$B$195="FY24")*(Raw_Export_Clean!$E$4:$E$195="Services")*Raw_Export_Clean!$F$4:$F$195) -> 600 | D37: =SUMPRODUCT((Raw_Export_Clean!$B$4:$B$195="FY24")*(Raw_Export_Clean!$E$4:$E$195="Services")*Raw_Export_Clean!$G$4:$G$195) -> 668.16 | E37: =D37-C37 -> 68.16 | F37: =IF(C37<>0,(D37-C37)/C37,0) -> 0.1136 | G37: GREEN | H37: GROW — above budget every month. Prioritise capacity expansion.
A38: Operations | B38: Cost | C38: =SUMPRODUCT((Raw_Export_Clean!$B$4:$B$195="FY24")*(Raw_Export_Clean!$E$4:$E$195="Operations")*Raw_Export_Clean!$F$4:$F$195) -> 1210 | D38: =SUMPRODUCT((Raw_Export_Clean!$B$4:$B$195="FY24")*(Raw_Export_Clean!$E$4:$E$195="Operations")*Raw_Export_Clean!$G$4:$G$195) -> 1300.03 | E38: =D38-C38 -> 90.03 | F38: =IF(C38<>0,(D38-C38)/C38,0) -> 0.074404959 | G38: RED | H38: CONTROL — cost inflation accelerating in FY24. Procurement audit needed.
A39: Sales | B39: Cost | C39: =SUMPRODUCT((Raw_Export_Clean!$B$4:$B$195="FY24")*(Raw_Export_Clean!$E$4:$E$195="Sales")*Raw_Export_Clean!$F$4:$F$195) -> 275 | D39: =SUMPRODUCT((Raw_Export_Clean!$B$4:$B$195="FY24")*(Raw_Export_Clean!$E$4:$E$195="Sales")*Raw_Export_Clean!$G$4:$G$195) -> 278.07 | E39: =D39-C39 -> 3.07 | F39: =IF(C39<>0,(D39-C39)/C39,0) -> 0.011163636 | G39: AMBER | H39: HOLD — near budget. Monitor incentive structure vs revenue output.
A40: Marketing | B40: Cost | C40: =SUMPRODUCT((Raw_Export_Clean!$B$4:$B$195="FY24")*(Raw_Export_Clean!$E$4:$E$195="Marketing")*Raw_Export_Clean!$F$4:$F$195) -> 225 | D40: =SUMPRODUCT((Raw_Export_Clean!$B$4:$B$195="FY24")*(Raw_Export_Clean!$E$4:$E$195="Marketing")*Raw_Export_Clean!$G$4:$G$195) -> 248.25 | E40: =D40-C40 -> 23.25 | F40: =IF(C40<>0,(D40-C40)/C40,0) -> 0.10333333 | G40: RED | H40: REVIEW — significant FY24 overrun. Demand ROI accountability.
A41: HR | B41: Cost | C41: =SUMPRODUCT((Raw_Export_Clean!$B$4:$B$195="FY24")*(Raw_Export_Clean!$E$4:$E$195="HR")*Raw_Export_Clean!$F$4:$F$195) -> 165 | D41: =SUMPRODUCT((Raw_Export_Clean!$B$4:$B$195="FY24")*(Raw_Export_Clean!$E$4:$E$195="HR")*Raw_Export_Clean!$G$4:$G$195) -> 172.41 | E41: =D41-C41 -> 7.41 | F41: =IF(C41<>0,(D41-C41)/C41,0) -> 0.044909091 | G41: AMBER | H41: WATCH — attrition costs rising. Retention intervention in Q3 FY25.
A42: Finance & Admin | B42: Cost | C42: =SUMPRODUCT((Raw_Export_Clean!$B$4:$B$195="FY24")*(Raw_Export_Clean!$E$4:$E$195="Finance & Admin")*Raw_Export_Clean!$F$4:$F$195) -> 110 | D42: =SUMPRODUCT((Raw_Export_Clean!$B$4:$B$195="FY24")*(Raw_Export_Clean!$E$4:$E$195="Finance & Admin")*Raw_Export_Clean!$G$4:$G$195) -> 111.14 | E42: =D42-C42 -> 1.14 | F42: =IF(C42<>0,(D42-C42)/C42,0) -> 0.010363636 | G42: GREEN | H42: HOLD — tightly controlled. No action required.
A43: KEY FINDING: Product B is in structural decline (-13% avg FY24). Operations cost inflation is accelerating (+7% avg FY24). Together these two lines account for 80%+ of total adverse variance. CFO action: freeze Product B budgeted growth in FY25 and initiate procurement review for Operations by Q1 FY25.
